compare_string_version/__init__.py
compare_string_version/compare.py
compare_string_version-0.1.0.dist-info/LICENSE.txt
compare_string_version-0.1.0.dist-info/METADATA
compare_string_version-0.1.0.dist-info/WHEEL
compare_string_version-0.1.0.dist-info/top_level.txt
compare_string_version-0.1.0.dist-info/RECORD
