Metadata-Version: 2.1
Name: compare-string-version
Version: 0.1.0
Summary: accepts 2 version string as input and returns whether one is greater than, equal, or less than the other
Home-page: https://github.com/miguelluiz/compare_string_version
Author: Miguel Almeida
Author-email: mplabdev@gmail.com
License: MIT
Download-URL: https://github.com/miguelluiz/compare_string_version/archive/v_01.tar.gz
Keywords: Compare,version control,version string as input
Platform: UNKNOWN
Classifier: Development Status :: 3 - Alpha
Classifier: Intended Audience :: Developers
Classifier: Topic :: Software Development :: Build Tools
Classifier: Topic :: Software Development :: Internationalization
Classifier: Operating System :: OS Independent
Classifier: License :: OSI Approved :: MIT License
Classifier: Programming Language :: Python :: 3
Classifier: Programming Language :: Python :: 3.4
Classifier: Programming Language :: Python :: 3.5
Classifier: Programming Language :: Python :: 3.6
Classifier: Programming Language :: Python :: 3.7
